{
  "collapse-filter": false,
  "search": "",
  "showTags": false,
  "showAttachments": false,
  "hideUnresolved": false,
  "showOrphans": false,
  "collapse-color-groups": false,
  "colorGroups": [
    {
      "query": "tag:#English",
      "color": {
        "a": 1,
        "rgb": 14048348
      }
    },
    {
      "query": "tag:#WorldCard",
      "color": {
        "a": 1,
        "rgb": 14069084
      }
    },
    {
      "query": "tag:#八股文",
      "color": {
        "a": 1,
        "rgb": 11392604
      }
    }
  ],
  "collapse-display": false,
  "showArrow": false,
  "textFadeMultiplier": 0,
  "nodeSizeMultiplier": 1,
  "lineSizeMultiplier": 1,
  "collapse-forces": true,
  "centerStrength": 0.518713248970312,
  "repelStrength": 10,
  "linkStrength": 1,
  "linkDistance": 250,
  "scale": 0.22920135941751313,
  "close": true
}